comber/__init__.py
comber/combinator.py
comber/extras.py
comber/parser.py
comber/py.typed
comber-1.0.1.dist-info/licenses/LICENSE.txt
comber-1.0.1.dist-info/METADATA
comber-1.0.1.dist-info/WHEEL
comber-1.0.1.dist-info/top_level.txt
comber-1.0.1.dist-info/RECORD
