Metadata-Version: 2.4
Name: comber
Version: 1.0.1
Summary: Parser combinator library with a BNF-esque interface
Author-email: Ray Wallace III <rwallace3@proton.me>
Project-URL: Homepage, https://github.com/faboo/comber
Project-URL: Repository, https://github.com/faboo/comber.git
Keywords: parser,combinator,parsing,compiler
Classifier: Programming Language :: Python :: 3
Classifier: Operating System :: OS Independent
Classifier: Intended Audience :: Developers
Classifier: License :: OSI Approved :: GNU Lesser General Public License v2 (LGPLv2)
Classifier: Topic :: Software Development :: Compilers
Classifier: Topic :: Text Processing
Classifier: Typing :: Typed
Requires-Python: >=3.10
License-File: LICENSE.txt
Provides-Extra: dev
Requires-Dist: tox; extra == "dev"
Dynamic: license-file
